{
	"schemaVersion": "0.1.0",
	"name": "New saved link - no AI",
	"behavior": "create",
	"noteContentFormat": "{{content}}",
	"properties": [
		{
			"name": "title",
			"value": "{{title}}",
			"type": "text"
		},
		{
			"name": "source",
			"value": "{{url}}",
			"type": "text"
		},
		{
			"name": "author",
			"value": "{{author|split:\\\", \\\"|wikilink|join}}",
			"type": "multitext"
		},
		{
			"name": "publishedDate",
			"value": "{{published}}",
			"type": "text"
		},
		{
			"name": "created",
			"value": "{{date}}",
			"type": "date"
		},
		{
			"name": "description",
			"value": "{{description}}",
			"type": "text"
		},
		{
			"name": "tags",
			"value": "clippings",
			"type": "multitext"
		}
	],
	"triggers": [],
	"noteNameFormat": "{{date|date:YYYY-MM-DD}} - {{title}}",
	"path": "Clippings"
}